djtriggers/__init__.py
djtriggers/checks.py
djtriggers/exceptions.py
djtriggers/locking.py
djtriggers/logic.py
djtriggers/managers.py
djtriggers/models.py
djtriggers/tasks.py
djtriggers/loggers/__init__.py
djtriggers/loggers/base.py
djtriggers/loggers/database.py
djtriggers/loggers/python_logging.py
djtriggers/management/__init__.py
djtriggers/management/commands/__init__.py
djtriggers/management/commands/clean_triggers.py
djtriggers/management/commands/process_triggers.py
djtriggers/migrations/0001_initial.py
djtriggers/migrations/0001_squashed_0006_auto_20171003_0945.py
djtriggers/migrations/0002_auto_20151208_1454.py
djtriggers/migrations/0003_auto_20160512_0847.py
djtriggers/migrations/0004_auto_20170216_1007.py
djtriggers/migrations/0005_trigger_successful.py
djtriggers/migrations/0006_auto_20171003_0945.py
djtriggers/migrations/0007_auto_20201001_1530.py
djtriggers/migrations/__init__.py
djtriggers/tests/__init__.py
djtriggers/tests/models.py
djtriggers/tests/test_dummy.py
djtriggers/tests/test_logic.py
djtriggers/tests/test_models.py
djtriggers/tests/factories/__init__.py
djtriggers/tests/factories/triggers.py
django_triggers-2.1.5.dist-info/LICENSE.txt
django_triggers-2.1.5.dist-info/METADATA
django_triggers-2.1.5.dist-info/WHEEL
django_triggers-2.1.5.dist-info/top_level.txt
django_triggers-2.1.5.dist-info/RECORD
