Metadata-Version: 2.1
Name: django-triggers
Version: 2.1.5
Summary: Framework to create and process triggers.
Home-page: https://github.com/vikingco/django-triggers
Author: Unleashed NV
Author-email: operations@unleashed.be
License: BSD
Platform: UNKNOWN
Classifier: Intended Audience :: Developers
Classifier: Programming Language :: Python
Classifier: Operating System :: OS Independent
Classifier: Environment :: Web Environment
Classifier: Framework :: Django
